{"cameraMode":{"drawMode":0,"name":"Shaded","section":"Shading Mode"},"sceneLighting":true,"audioPlay":false,"sceneViewState":{"m_AlwaysRefresh":false,"showFog":true,"showSkybox":true,"showFlares":true,"showImageEffects":true,"showParticleSystems":true,"showVisualEffectGraphs":true,"m_FxEnabled":true},"in2DMode":false,"pivot":{"x":9.210550308227539,"y":2.011185646057129,"z":1.917159914970398},"rotation":{"x":0.09127549827098847,"y":-0.0939687192440033,"z":0.008688794448971749,"w":0.9914280772209168},"size":6.134650230407715,"orthographic":false}